pyxides/__init__.py
pyxides/containers.py
pyxides/getitem.py
pyxides/grouping.py
pyxides/pprint.py
pyxides/typing.py
pyxides/vectorize.py
pyxides-0.3.0.dist-info/LICENSE
pyxides-0.3.0.dist-info/METADATA
pyxides-0.3.0.dist-info/WHEEL
pyxides-0.3.0.dist-info/top_level.txt
pyxides-0.3.0.dist-info/RECORD
